{
  "contract_id": "meteocat-weather-stations-metadata-landing-contract",
  "dataset_id": "meteocat-weather",
  "source": "meteocat",
  "resource": "stations-metadata",
  "layer": "landing",
  "status": "draft",
  "validation_level": "minimal",
  "schema_ref": "../schemas/stations-metadata.schema.json",
  "description": "Minimal landing contract for Meteocat stations metadata.",
  "allowed_evolution": {
    "additional_fields": true,
    "field_removal": "review_required",
    "type_changes": "review_required"
  },
  "known_limitations": [
    "Schema is intentionally permissive.",
    "Real API payloads still require broader verification.",
    "This is not an official upstream contract."
  ]
}
